ndx_labmetadata_giocomo/__init__.py
ndx_labmetadata_giocomo/test.py
ndx_labmetadata_giocomo/spec/ndx-labmetadata-giocomo.extensions.yaml
ndx_labmetadata_giocomo/spec/ndx-labmetadata-giocomo.namespace.yaml
ndx_labmetadata_giocomo-0.0.1.dist-info/LICENSE
ndx_labmetadata_giocomo-0.0.1.dist-info/METADATA
ndx_labmetadata_giocomo-0.0.1.dist-info/WHEEL
ndx_labmetadata_giocomo-0.0.1.dist-info/top_level.txt
ndx_labmetadata_giocomo-0.0.1.dist-info/RECORD
